easy_smr/__init__.py
easy_smr/__main__.py
easy_smr/commands/__init__.py
easy_smr/commands/build.py
easy_smr/commands/cloud.py
easy_smr/commands/helpers.py
easy_smr/commands/initialize.py
easy_smr/commands/local.py
easy_smr/commands/push.py
easy_smr/config/__init__.py
easy_smr/config/config.py
easy_smr/sagemaker/__init__.py
easy_smr/sagemaker/sagemaker.py
easy_smr/template/easy_smr_base/.Rprofile
easy_smr/template/easy_smr_base/.dockerignore
easy_smr/template/easy_smr_base/Dockerfile
easy_smr/template/easy_smr_base/build.sh
easy_smr/template/easy_smr_base/executor.sh
easy_smr/template/easy_smr_base/push.sh
easy_smr/template/easy_smr_base/renv.lock
easy_smr/template/easy_smr_base/local_test/deploy_local.sh
easy_smr/template/easy_smr_base/local_test/make_local.sh
easy_smr/template/easy_smr_base/local_test/process_local.sh
easy_smr/template/easy_smr_base/local_test/train_local.sh
easy_smr/template/easy_smr_base/local_test/test_dir/input/data/training/.gitkeep
easy_smr/template/easy_smr_base/local_test/test_dir/model/.gitkeep
easy_smr/template/easy_smr_base/local_test/test_dir/output/.gitkeep
easy_smr/template/easy_smr_base/prediction/plumber.R
easy_smr/template/easy_smr_base/prediction/serve
easy_smr/template/easy_smr_base/processing/.gitkeep
easy_smr/template/easy_smr_base/renv/.gitignore
easy_smr/template/easy_smr_base/renv/activate.R
easy_smr/template/easy_smr_base/renv/settings.json
easy_smr/template/easy_smr_base/training/train
easy_smr/template/easy_smr_base/training/training.R
easy_smr-0.1.12.dist-info/LICENSE
easy_smr-0.1.12.dist-info/METADATA
easy_smr-0.1.12.dist-info/WHEEL
easy_smr-0.1.12.dist-info/entry_points.txt
easy_smr-0.1.12.dist-info/top_level.txt
easy_smr-0.1.12.dist-info/RECORD
