Metadata-Version: 2.1
Name: easy-smr
Version: 0.1.12
Summary: Easy Sagemaker Ops for R projects
Author: Prateek
Author-email: prteek@icloud.com
Requires-Python: >=3.11
License-File: LICENSE
Requires-Dist: click<8.1.99,>=8.1.7
Requires-Dist: docker<7.2.0,>=7.1.0
Requires-Dist: sagemaker>=2.243.0
